<?xml version="1.0" encoding="UTF-8"?>
<Export generator="Cache" version="24" zv="Cache for Windows (x86-64) 2010.2.8 (Build 1104U)" ts="2014-03-11 16:42:07">
<Class name="websys.Patch">
<Description>
Very simple class to handle interface for patching.
This is by design simple so we don't have to patch it !!!
This should therefore not be used by parts of the application other than patching.</Description>
<ClassType/>
<ProcedureBlock>0</ProcedureBlock>
<Super>%Library.RegisteredObject</Super>
<TimeChanged>60506,62126</TimeChanged>
<TimeCreated>58658,66407</TimeCreated>

<Method name="Execute">
<Description>
Execute a expression.
Used (ONLY) by patch utilities.</Description>
<Final>0</Final>
<ClassMethod>1</ClassMethod>
<CodeMode>code</CodeMode>
<FormalSpec>exp:%Library.String</FormalSpec>
<Private>0</Private>
<ReturnType>%Library.String</ReturnType>
<SqlProc>0</SqlProc>
</Method>

<Method name="xxxBackupSource">
<Final>0</Final>
<ClassMethod>1</ClassMethod>
<CodeMode>code</CodeMode>
<FormalSpec>MEDnamespace:%Library.String,WEBnamespace:%Library.String,CachePathToMBackup:%Library.String</FormalSpec>
<Private>0</Private>
<ReturnType>%Library.String</ReturnType>
<SqlProc>0</SqlProc>
</Method>

<Method name="xxxDropTableDefinition">
<Final>0</Final>
<ClassMethod>1</ClassMethod>
<CodeMode>code</CodeMode>
<FormalSpec>AllClassNames:%Library.String</FormalSpec>
<Private>0</Private>
<ReturnType>%Library.String</ReturnType>
<SqlProc>0</SqlProc>
</Method>

<Method name="xxxExecuteGogen">
<Final>0</Final>
<ClassMethod>1</ClassMethod>
<CodeMode>code</CodeMode>
<FormalSpec>FileName:%Library.String</FormalSpec>
<Private>0</Private>
<ReturnType>%Library.Boolean</ReturnType>
<SqlProc>0</SqlProc>
</Method>

<Method name="xxxExecuteRomf">
<Final>0</Final>
<ClassMethod>1</ClassMethod>
<CodeMode>code</CodeMode>
<FormalSpec>FileName:%Library.String</FormalSpec>
<Private>0</Private>
<ReturnType>%Library.Boolean</ReturnType>
<SqlProc>0</SqlProc>
</Method>

<Method name="xxxGetCSPPhysPaths">
<Final>0</Final>
<ClassMethod>1</ClassMethod>
<CodeMode>code</CodeMode>
<FormalSpec>WebSourceNS:%Library.String</FormalSpec>
<Private>0</Private>
<ReturnType>%Library.String</ReturnType>
<SqlProc>0</SqlProc>
</Method>

<Method name="xxxGetMEDNSpaces">
<Final>0</Final>
<ClassMethod>0</ClassMethod>
<CodeMode>code</CodeMode>
<FormalSpec>MedSourceNS:%Library.String</FormalSpec>
<Private>0</Private>
<ReturnType>%Library.String</ReturnType>
<SqlProc>0</SqlProc>
</Method>

<Method name="xxxGetNSDirectories">
<Final>0</Final>
<ClassMethod>1</ClassMethod>
<CodeMode>code</CodeMode>
<FormalSpec><![CDATA[&MedData:%Library.String,&MedSource:%Library.String,&WebSource:%Library.String]]></FormalSpec>
<Private>0</Private>
<ReturnType>%Library.String</ReturnType>
<SqlProc>0</SqlProc>
</Method>

<Method name="xxxGetNSMounted">
<Final>0</Final>
<ClassMethod>1</ClassMethod>
<CodeMode>code</CodeMode>
<FormalSpec>MedData:%Library.String,MedSource:%Library.String,WebSource:%Library.String</FormalSpec>
<Private>0</Private>
<ReturnType>%Library.String</ReturnType>
<SqlProc>0</SqlProc>
</Method>

<Method name="xxxGetValidNamespaceNames">
<Final>0</Final>
<ClassMethod>1</ClassMethod>
<CodeMode>code</CodeMode>
<FormalSpec><![CDATA[&WebSourceList:%Library.String,&MedSourceList:%Library.String]]></FormalSpec>
<Private>0</Private>
<SqlProc>0</SqlProc>
</Method>

<Method name="xxxImportMDD">
<Final>0</Final>
<ClassMethod>1</ClassMethod>
<CodeMode>code</CodeMode>
<FormalSpec>Filename:%Library.String,MEDNamespace:%Library.String</FormalSpec>
<Private>0</Private>
<ReturnType>%Library.String</ReturnType>
<SqlProc>0</SqlProc>
</Method>

<Method name="xxxImportMEDRoutines">
<Final>0</Final>
<ClassMethod>1</ClassMethod>
<CodeMode>code</CodeMode>
<FormalSpec>Filename:%Library.String,MEDNamespace:%Library.String</FormalSpec>
<Private>0</Private>
<ReturnType>%Library.String</ReturnType>
<SqlProc>0</SqlProc>
</Method>

<Method name="xxxImportMergeSS">
<Final>0</Final>
<ClassMethod>1</ClassMethod>
<CodeMode>code</CodeMode>
<FormalSpec>Filename:%Library.String,MEDNamespace:%Library.String</FormalSpec>
<Private>0</Private>
<ReturnType>%Library.String</ReturnType>
<SqlProc>0</SqlProc>
</Method>

<Method name="xxxMDDTableNamesGet">
<Final>0</Final>
<ClassMethod>1</ClassMethod>
<CodeMode>code</CodeMode>
<FormalSpec/>
<Private>0</Private>
<ReturnType>%Library.String</ReturnType>
<SqlProc>0</SqlProc>
</Method>

<Method name="xxxRebuildMDDTable">
<Final>0</Final>
<ClassMethod>1</ClassMethod>
<CodeMode>code</CodeMode>
<FormalSpec>AllTableNames:%Library.String</FormalSpec>
<Private>0</Private>
<ReturnType>%Library.Boolean</ReturnType>
<SqlProc>0</SqlProc>
</Method>

<Method name="xxxRestoreSource">
<Final>0</Final>
<ClassMethod>1</ClassMethod>
<CodeMode>code</CodeMode>
<FormalSpec>MEDnamespace:%Library.String,WEBnamespace:%Library.String,CachePathToMBackup:%Library.String</FormalSpec>
<Private>0</Private>
<ReturnType>%Library.String</ReturnType>
<SqlProc>0</SqlProc>
</Method>

<Method name="xxxRestoreTKImport">
<Final>0</Final>
<ClassMethod>1</ClassMethod>
<CodeMode>code</CodeMode>
<FormalSpec>CachePathToTKImport:%Library.String,WEBnamespace:%Library.String</FormalSpec>
<Private>0</Private>
<ReturnType>%Library.String</ReturnType>
<SqlProc>0</SqlProc>
</Method>

<Method name="xxxRunTKImport">
<Description>
Execute tkImport in silent non-interactive mode.
</Description>
<Final>0</Final>
<ClassMethod>1</ClassMethod>
<CodeMode>code</CodeMode>
<FormalSpec>CachePathToPatches:%Library.String,CachePathToViews:%Library.String,OVRPathToScripts:%Library.String</FormalSpec>
<Private>0</Private>
<ReturnType>%Library.String</ReturnType>
<SqlProc>0</SqlProc>
</Method>
</Class>
</Export>
